control/fa16_wrapped.sv
// fa16_wrapped.sv

// This is the macro Defination
// Black Box: Pins are matched with those in the layout
// Synthesis / PnR should treate the module as a hard-coded macro, it's internal implementation comes from GDS

/*
Testbench Annotation:
// When SIM_REV_MODEL is defined: behavioural reversible "inverter-style" model for simulation
// Otherwise: black-box macro for synthesis / Place & Route
*/

`ifdef SIM_REV_MODEL

// Simulation behavioural model of fa16_rev_wrapped.
// Simple self-inverse reversible mapping using bitwise inversion.
module fa16_rev_wrapped (
`ifdef USE_POWER_PINS
    inout wire VDD,
    inout wire VSS,
`endif
    input  logic        dir,     // 0: a-side -> s-side, 1: s-side -> a-side

    inout  wire [15:0]  a,
    inout  wire [15:0]  a_not,
    inout  wire [15:0]  b,
    inout  wire [15:0]  b_not,
    inout  wire         c0_f,
    inout  wire         c0_f_not,
    inout  wire         z,
    inout  wire         z_not,

    inout  wire [15:0]  s,
    inout  wire [15:0]  s_not,
    inout  wire [15:0]  a_b,
    inout  wire [15:0]  a_not_b,
    inout  wire         c0_b,
    inout  wire         c0_b_not,
    inout  wire         c15,
    inout  wire         c15_not
);
    // Internal drivers for all pins
    logic [15:0] a_drv, a_not_drv;
    logic [15:0] b_drv, b_not_drv;
    logic        c0_f_drv, c0_f_not_drv;
    logic        z_drv,    z_not_drv;

    logic [15:0] s_drv, s_not_drv;
    logic [15:0] a_b_drv, a_not_b_drv;
    logic        c0_b_drv, c0_b_not_drv;
    logic        c15_drv,  c15_not_drv;

    // Connect drivers to the inout pins
    assign a        = a_drv;
    assign a_not    = a_not_drv;
    assign b        = b_drv;
    assign b_not    = b_not_drv;
    assign c0_f     = c0_f_drv;
    assign c0_f_not = c0_f_not_drv;
    assign z        = z_drv;
    assign z_not    = z_not_drv;

    assign s        = s_drv;
    assign s_not    = s_not_drv;
    assign a_b      = a_b_drv;
    assign a_not_b  = a_not_b_drv;
    assign c0_b     = c0_b_drv;
    assign c0_b_not = c0_b_not_drv;
    assign c15      = c15_drv;
    assign c15_not  = c15_not_drv;

    // Simple reversible behaviour:
    // dir = 0: (a,b,c0_f,z) -> (s,a_b,c0_b,c15) = bitwise inversion
    // dir = 1: (s,a_b,c0_b,c15) -> (a,b,c0_f,z) = bitwise inversion
    //
    // Apply it twice and we can get back the original input.
    always @* begin
        // Default all drivers to high-Z so we never fight with fa16_rev_ctrl
        a_drv        = {16{1'bz}};
        a_not_drv    = {16{1'bz}};
        b_drv        = {16{1'bz}};
        b_not_drv    = {16{1'bz}};
        c0_f_drv     = 1'bz;
        c0_f_not_drv = 1'bz;
        z_drv        = 1'bz;
        z_not_drv    = 1'bz;

        s_drv        = {16{1'bz}};
        s_not_drv    = {16{1'bz}};
        a_b_drv      = {16{1'bz}};
        a_not_b_drv  = {16{1'bz}};
        c0_b_drv     = 1'bz;
        c0_b_not_drv = 1'bz;
        c15_drv      = 1'bz;
        c15_not_drv  = 1'bz;

        if (dir == 1'b0) begin
            // Forward: drive S-side from A-side (invert)
            s_drv        = ~a;
            s_not_drv    =  a;       // double-rail: s_not = ~s = a
            a_b_drv      = ~b;
            a_not_b_drv  =  b;
            c0_b_drv     = ~c0_f;
            c0_b_not_drv =  c0_f;
            c15_drv      = ~z;
            c15_not_drv  =  z;
            // A-side pins are left Z here; fa16_rev_ctrl drives them.
        end
        else begin
            // Backward: drive A-side from S-side (invert)
            a_drv        = ~s;
            a_not_drv    =  s;
            b_drv        = ~a_b;
            b_not_drv    =  a_b;
            c0_f_drv     = ~c0_b;
            c0_f_not_drv =  c0_b;
            z_drv        = ~c15;
            z_not_drv    =  c15;
            // S-side pins are left Z here; fa16_rev_ctrl drives them.
        end
    end

endmodule

`else

// Synthesis / Place & Route version: real hard macro, no behaviour.
// This is the one we will use in LibreLane.

(* black_box, keep_hierarchy = "yes" *)
module fa16_rev_wrapped (
`ifdef USE_POWER_PINS
    inout wire VDD,
    inout wire VSS,
`endif

    inout  wire [15:0] a,
    inout  wire [15:0] a_not,
    inout  wire [15:0] b,
    inout  wire [15:0] b_not,
    inout  wire        c0_f,
    inout  wire        c0_f_not,
    inout  wire        z,
    inout  wire        z_not,

    inout  wire [15:0] s,
    inout  wire [15:0] s_not,
    inout  wire [15:0] a_b,
    inout  wire [15:0] a_not_b,
    inout  wire        c0_b,
    inout  wire        c0_b_not,
    inout  wire        c15,
    inout  wire        c15_not
);
// Real RTL content comes for custom layout
endmodule

`endif

control/fa16_rev_control.sv
// fa16_rev_control.sv
// This takes in fa16_rev_wrapped, and achieves bidirectional control under signal 'dir'
/*
Wrapping Structure:
Outter Logic <-> f_/r_ Port <-> fa16_rev_ctrl <-> pin_* bus <-> fa16_rev_wrapped
- fa16_rev_wrapped: the macro defined
- pin_*: physical wire connected to the macro pin, tristate bus
- fa16_rev_ctrl: control logic actually defined in the module
- f_/r_ Port: What the upper level(testbench) actually see
- Outter Logic: Testbench Written


*/

module fa16_rev_ctrl (
`ifdef USE_POWER_PINS
    inout wire VDD,
    inout wire VSS,
`endif
    input  wire        dir,      // 0: forward  (A,B,C0_f,Z -> S,a_b,C0_b,C15)
                                 // 1: backward (S,a_b,C0_b,C15 -> A,B,C0_f,Z)

    // Forward Interface: Used when dir == 0
    // Input: A, B, C0_f, z
    input  wire [15:0] f_a,
    input  wire [15:0] f_b,
    input  wire        f_c0_f,
    input  wire        f_z,

    // Output: S, A_B, C0_b, C15
    output wire [15:0] f_s,
    output wire [15:0] f_a_b,
    output wire        f_c0_b,
    output wire        f_c15,

    // Backward Interface: Used when dir == 1
    // Output: S, A_B, C0_b, C15
    input  wire [15:0] r_s,
    input  wire [15:0] r_a_b,
    input  wire        r_c0_b,
    input  wire        r_c15,

    // Output: A, B, C0_f, z (Original input recovered)
    output wire [15:0] r_a,
    output wire [15:0] r_b,
    output wire        r_c0_f,
    output wire        r_z
);

    // ============================================================
    // 1) Define the physical pin (bus) connected to the macro 
    //    Allowing multiple tri-state driver
    // ============================================================
    tri [15:0] pin_a;
    tri [15:0] pin_a_not;
    tri [15:0] pin_b;
    tri [15:0] pin_b_not;
    tri        pin_c0_f;
    tri        pin_c0_f_not;
    tri        pin_z;
    tri        pin_z_not;

    tri [15:0] pin_s;
    tri [15:0] pin_s_not;
    tri [15:0] pin_a_b;
    tri [15:0] pin_a_not_b;
    tri        pin_c0_b;
    tri        pin_c0_b_not;
    tri        pin_c15;
    tri        pin_c15_not;

    // ============================================================
    // 2) Instantiating the reversible adder core
    // ============================================================
    `ifdef SIM_REV_MODEL
        // SImulationL Explicit Dir

        fa16_rev_wrapped u_rev (
        `ifdef USE_POWER_PINS
            .VDD     (VDD),
            .VSS     (VSS),
        `endif
            // pass direction into the behavioural macro
            .dir     (dir), 

            .a        (pin_a),
            .a_not    (pin_a_not),
            .b        (pin_b),
            .b_not    (pin_b_not),
            .c0_f     (pin_c0_f),
            .c0_f_not (pin_c0_f_not),
            .z        (pin_z),
            .z_not    (pin_z_not),

            .s        (pin_s),
            .s_not    (pin_s_not),
            .a_b      (pin_a_b),
            .a_not_b  (pin_a_not_b),
            .c0_b     (pin_c0_b),
            .c0_b_not (pin_c0_b_not),
            .c15      (pin_c15),
            .c15_not  (pin_c15_not)
        );

`else
    // Synthesis / Place & Route: hard macro without dir
    fa16_rev_wrapped u_rev (
    `ifdef USE_POWER_PINS
        .VDD     (VDD),
        .VSS     (VSS),
    `endif
        .a        (pin_a),
        .a_not    (pin_a_not),
        .b        (pin_b),
        .b_not    (pin_b_not),
        .c0_f     (pin_c0_f),
        .c0_f_not (pin_c0_f_not),
        .z        (pin_z),
        .z_not    (pin_z_not),

        .s        (pin_s),
        .s_not    (pin_s_not),
        .a_b      (pin_a_b),
        .a_not_b  (pin_a_not_b),
        .c0_b     (pin_c0_b),
        .c0_b_not (pin_c0_b_not),
        .c15      (pin_c15),
        .c15_not  (pin_c15_not)
    );

`endif

    // ============================================================
    // 3) Forward-Backward control drive
    //    This is implemented using pure combinational logic
    //
    //   - dir = 0: Forward
    //       Outside -> Macro
    //         A, B, C0_f, Z  Drive pin_a/pin_b/pin_c0_f/pin_z(And it's corresponding _not)
    //       Macro -> Ourside
    //         pin_s, pin_a_b, pin_c0_b, pin_c15 for outside read
    //
    //   - dir = 1: Backward
    //       Outside -> Macro
    //         S, A_B, C0_b, C15 Drives pin_s/pin_a_b/pin_c0_b/pin_c15(And it's corresponding _not)
    //       Macro -> Ourside
    //         pin_a, pin_b, pin_c0_f, pin_z for outside read
    //
    //   The tri-state bus and a one-bit dir is to ensure that each pin has only one driver at any time
    // ============================================================

    // 3.1 Forward Drive, when Dir == 0
    // Input: A, B, C0_f, z
    assign pin_a        = (dir == 1'b0) ? f_a       : 16'hzzzz;
    assign pin_a_not    = (dir == 1'b0) ? ~f_a      : 16'hzzzz;

    assign pin_b        = (dir == 1'b0) ? f_b       : 16'hzzzz;
    assign pin_b_not    = (dir == 1'b0) ? ~f_b      : 16'hzzzz;

    assign pin_c0_f     = (dir == 1'b0) ? f_c0_f    : 1'bz;
    assign pin_c0_f_not = (dir == 1'b0) ? ~f_c0_f   : 1'bz;

    assign pin_z        = (dir == 1'b0) ? f_z       : 1'bz;
    assign pin_z_not    = (dir == 1'b0) ? ~f_z      : 1'bz;

    // Output side S, A_B, C0_b, C15 is drived by the macro, it is read-only
    assign f_s    = pin_s;      
    assign f_a_b  = pin_a_b;
    assign f_c0_b = pin_c0_b;
    assign f_c15  = pin_c15;

    // Backward Drive, when Dir == 1
    // Input: S, A_B, C0_b, C15
    assign pin_s        = (dir == 1'b1) ? r_s       : 16'hzzzz;
    assign pin_s_not    = (dir == 1'b1) ? ~r_s      : 16'hzzzz;

    assign pin_a_b      = (dir == 1'b1) ? r_a_b     : 16'hzzzz;
    assign pin_a_not_b  = (dir == 1'b1) ? ~r_a_b    : 16'hzzzz;

    assign pin_c0_b     = (dir == 1'b1) ? r_c0_b    : 1'bz;
    assign pin_c0_b_not = (dir == 1'b1) ? ~r_c0_b   : 1'bz;

    assign pin_c15      = (dir == 1'b1) ? r_c15     : 1'bz;
    assign pin_c15_not  = (dir == 1'b1) ? ~r_c15    : 1'bz;

    assign r_a     = pin_a;       
    assign r_b     = pin_b;
    assign r_c0_f  = pin_c0_f;
    assign r_z     = pin_z;

    // ============================================================
    // 4) Optional Sanity Check (generated by ChatGPT)
    //    To check whether the 'dir' is clean (cannot be both 0 and 1, or being contaminated by X)
    // ============================================================
`ifndef SYNTHESIS
    // Throw error if this happens
    always @(*) begin
        if (dir !== 1'b0 && dir !== 1'b1) begin
            $error("fa16_rev_ctrl: dir is X or Z, this will break reversibility.");
        end
    end
`endif

endmodule

control/tb_fa16_rev_control.sv
// tb_fa16_rev_control.sv
`timescale 1ns/1ps
`define USE_POWER_PINS   // keep consistent with your DUT

module tb_fa16_rev_ctrl;

    // Direction control
    reg         dir;

    // Forward interface (dir = 0)
    reg  [15:0] f_a;
    reg  [15:0] f_b;
    reg         f_c0_f;
    reg         f_z;

    wire [15:0] f_s;
    wire [15:0] f_a_b;
    wire        f_c0_b;
    wire        f_c15;

    // Backward interface (dir = 1)
    reg  [15:0] r_s;
    reg  [15:0] r_a_b;
    reg         r_c0_b;
    reg         r_c15;

    wire [15:0] r_a;
    wire [15:0] r_b;
    wire        r_c0_f;
    wire        r_z;

`ifdef USE_POWER_PINS
    wire VDD = 1'b1;
    wire VSS = 1'b0;
`endif

    // Instantiate DUT
    fa16_rev_ctrl dut (
    `ifdef USE_POWER_PINS
        .VDD   (VDD),
        .VSS   (VSS),
    `endif
        .dir   (dir),

        .f_a   (f_a),
        .f_b   (f_b),
        .f_c0_f(f_c0_f),
        .f_z   (f_z),

        .f_s   (f_s),
        .f_a_b (f_a_b),
        .f_c0_b(f_c0_b),
        .f_c15 (f_c15),

        .r_s   (r_s),
        .r_a_b (r_a_b),
        .r_c0_b(r_c0_b),
        .r_c15 (r_c15),

        .r_a   (r_a),
        .r_b   (r_b),
        .r_c0_f(r_c0_f),
        .r_z   (r_z)
    );

    // For logging / checking
    integer i;
    integer error_count = 0;

    reg [15:0] orig_a, orig_b;
    reg        orig_c0_f, orig_z;
    reg [15:0] saved_s, saved_a_b;
    reg        saved_c0_b, saved_c15;

    // VCD dump
    initial begin
        $dumpfile("fa16_rev_ctrl_tb.vcd");
        $dumpvars(0, tb_fa16_rev_ctrl);
    end

    initial begin
        // Initial values
        dir      = 1'b0;
        f_a      = 16'h0000;
        f_b      = 16'h0000;
        f_c0_f   = 1'b0;
        f_z      = 1'b0;

        r_s      = 16'h0000;
        r_a_b    = 16'h0000;
        r_c0_b   = 1'b0;
        r_c15    = 1'b0;

        #10; // let things settle

        // Run multiple random tests
        for (i = 0; i < 100; i = i + 1) begin
            // -------------------------------
            // Step 1: Forward (dir = 0)
            // -------------------------------
            orig_a    = $random;
            orig_b    = $random;
            orig_c0_f = $random & 1'b1;
            orig_z    = $random & 1'b1;

            f_a      = orig_a;
            f_b      = orig_b;
            f_c0_f   = orig_c0_f;
            f_z      = orig_z;

            dir      = 1'b0;

            #20; // allow combinational logic to settle

            saved_s    = f_s;
            saved_a_b  = f_a_b;
            saved_c0_b = f_c0_b;
            saved_c15  = f_c15;

            // -------------------------------
            // Step 2: Backward (dir = 1)
            // -------------------------------
            r_s    = saved_s;
            r_a_b  = saved_a_b;
            r_c0_b = saved_c0_b;
            r_c15  = saved_c15;

            #5;
            dir    = 1'b1;

            #20; // wait for backward propagation

            // -------------------------------
            // Step 3: Check round-trip
            // -------------------------------
            if (r_a    !== orig_a ||
                r_b    !== orig_b ||
                r_c0_f !== orig_c0_f ||
                r_z    !== orig_z) begin
                $display("[ERROR] iter %0d: round-trip mismatch", i);
                $display("        orig: A=%h B=%h C0=%b Z=%b",
                         orig_a, orig_b, orig_c0_f, orig_z);
                $display("        back: A=%h B=%h C0=%b Z=%b",
                         r_a, r_b, r_c0_f, r_z);
                error_count = error_count + 1;
            end
            else begin
                $display("[OK]    iter %0d: reversible round-trip passed.", i);
            end

            // Prepare for next iteration
            dir = 1'b0;
            #10;
        end

        $display("================================");
        $display("Simulation finished, error_count = %0d", error_count);
        if (error_count == 0)
            $display("All round-trip tests PASSED.");
        else
            $display("Some round-trip tests FAILED.");
        $display("================================");

        $finish;
    end

endmodule

control/fa16_rev_ctrl_tb.vcd
$date
	Mon Dec  1 00:33:51 2025
$end
$version
	Icarus Verilog
$end
$timescale
	1ps
$end
$scope module tb_fa16_rev_ctrl $end
$var wire 1 ! VDD $end
$var wire 1 " VSS $end
$var wire 1 # r_z $end
$var wire 1 $ r_c0_f $end
$var wire 16 % r_b [15:0] $end
$var wire 16 & r_a [15:0] $end
$var wire 16 ' f_s [15:0] $end
$var wire 1 ( f_c15 $end
$var wire 1 ) f_c0_b $end
$var wire 16 * f_a_b [15:0] $end
$var reg 1 + dir $end
$var reg 16 , f_a [15:0] $end
$var reg 16 - f_b [15:0] $end
$var reg 1 . f_c0_f $end
$var reg 1 / f_z $end
$var reg 16 0 orig_a [15:0] $end
$var reg 16 1 orig_b [15:0] $end
$var reg 1 2 orig_c0_f $end
$var reg 1 3 orig_z $end
$var reg 16 4 r_a_b [15:0] $end
$var reg 1 5 r_c0_b $end
$var reg 1 6 r_c15 $end
$var reg 16 7 r_s [15:0] $end
$var reg 16 8 saved_a_b [15:0] $end
$var reg 1 9 saved_c0_b $end
$var reg 1 : saved_c15 $end
$var reg 16 ; saved_s [15:0] $end
$var integer 32 < error_count [31:0] $end
$var integer 32 = i [31:0] $end
$scope module dut $end
$var wire 1 ! VDD $end
$var wire 1 " VSS $end
$var wire 1 + dir $end
$var wire 16 > f_a [15:0] $end
$var wire 16 ? f_a_b [15:0] $end
$var wire 16 @ f_b [15:0] $end
$var wire 1 ) f_c0_b $end
$var wire 1 . f_c0_f $end
$var wire 1 ( f_c15 $end
$var wire 16 A f_s [15:0] $end
$var wire 1 / f_z $end
$var wire 16 B pin_a [15:0] $end
$var wire 16 C pin_a_b [15:0] $end
$var wire 16 D pin_a_not [15:0] $end
$var wire 16 E pin_a_not_b [15:0] $end
$var wire 16 F pin_b [15:0] $end
$var wire 16 G pin_b_not [15:0] $end
$var wire 1 H pin_c0_b $end
$var wire 1 I pin_c0_b_not $end
$var wire 1 J pin_c0_f $end
$var wire 1 K pin_c0_f_not $end
$var wire 1 L pin_c15 $end
$var wire 1 M pin_c15_not $end
$var wire 16 N pin_s [15:0] $end
$var wire 16 O pin_s_not [15:0] $end
$var wire 1 P pin_z $end
$var wire 1 Q pin_z_not $end
$var wire 16 R r_a [15:0] $end
$var wire 16 S r_a_b [15:0] $end
$var wire 16 T r_b [15:0] $end
$var wire 1 5 r_c0_b $end
$var wire 1 $ r_c0_f $end
$var wire 1 6 r_c15 $end
$var wire 16 U r_s [15:0] $end
$var wire 1 # r_z $end
$scope module u_rev $end
$var wire 1 ! VDD $end
$var wire 1 " VSS $end
$var wire 16 V a [15:0] $end
$var wire 16 W a_b [15:0] $end
$var wire 16 X a_not [15:0] $end
$var wire 16 Y a_not_b [15:0] $end
$var wire 16 Z b [15:0] $end
$var wire 16 [ b_not [15:0] $end
$var wire 1 H c0_b $end
$var wire 1 I c0_b_not $end
$var wire 1 J c0_f $end
$var wire 1 K c0_f_not $end
$var wire 1 L c15 $end
$var wire 1 M c15_not $end
$var wire 1 + dir $end
$var wire 16 \ s [15:0] $end
$var wire 16 ] s_not [15:0] $end
$var wire 1 P z $end
$var wire 1 Q z_not $end
$var reg 16 ^ a_b_drv [15:0] $end
$var reg 16 _ a_drv [15:0] $end
$var reg 16 ` a_not_b_drv [15:0] $end
$var reg 16 a a_not_drv [15:0] $end
$var reg 16 b b_drv [15:0] $end
$var reg 16 c b_not_drv [15:0] $end
$var reg 1 d c0_b_drv $end
$var reg 1 e c0_b_not_drv $end
$var reg 1 f c0_f_drv $end
$var reg 1 g c0_f_not_drv $end
$var reg 1 h c15_drv $end
$var reg 1 i c15_not_drv $end
$var reg 16 j s_drv [15:0] $end
$var reg 16 k s_not_drv [15:0] $end
$var reg 1 l z_drv $end
$var reg 1 m z_not_drv $end
$upscope $end
$upscope $end
$upscope $end
$enddefinitions $end
$comment Show the parameter values. $end
$dumpall
$end
#0
$dumpvars
zm
zl
b0 k
b1111111111111111 j
0i
1h
zg
zf
0e
1d
bz c
bz b
bz a
b0 `
bz _
b1111111111111111 ^
b0 ]
b1111111111111111 \
b1111111111111111 [
b0 Z
b0 Y
b1111111111111111 X
b1111111111111111 W
b0 V
b0 U
b0 T
b0 S
b0 R
1Q
0P
b0 O
b1111111111111111 N
0M
1L
1K
0J
0I
1H
b1111111111111111 G
b0 F
b0 E
b1111111111111111 D
b1111111111111111 C
b0 B
b1111111111111111 A
b0 @
b1111111111111111 ?
b0 >
bx =
b0 <
bx ;
x:
x9
bx 8
b0 7
06
05
b0 4
x3
x2
bx 1
bx 0
0/
0.
b0 -
b0 ,
0+
b1111111111111111 *
1)
1(
b1111111111111111 '
b0 &
b0 %
0$
0#
0"
1!
$end
#10000
0Q
0K
b1010000101111110 G
b1010000101111110 [
b1100101011011011 D
b1100101011011011 X
1M
1i
0(
0L
0h
1I
1e
0)
0H
0d
b101111010000001 E
b101111010000001 Y
b101111010000001 `
b1010000101111110 *
b1010000101111110 ?
b1010000101111110 C
b1010000101111110 W
b1010000101111110 ^
b11010100100100 O
b11010100100100 ]
b11010100100100 k
b1100101011011011 '
b1100101011011011 A
b1100101011011011 N
b1100101011011011 \
b1100101011011011 j
1#
1P
1$
1J
b101111010000001 %
b101111010000001 T
b101111010000001 F
b101111010000001 Z
b11010100100100 &
b11010100100100 R
b11010100100100 B
b11010100100100 V
1/
1.
b101111010000001 -
b101111010000001 @
b11010100100100 ,
b11010100100100 >
13
12
b101111010000001 1
b11010100100100 0
b0 =
#30000
b1010000101111110 4
b1010000101111110 S
b1100101011011011 7
b1100101011011011 U
0:
09
b1010000101111110 8
b1100101011011011 ;
#35000
0m
0g
b1010000101111110 c
b1100101011011011 a
b1100101011011011 D
b1100101011011011 X
b1010000101111110 G
b1010000101111110 [
0K
0Q
1#
1P
1l
1$
1J
1f
b101111010000001 %
b101111010000001 T
b101111010000001 F
b101111010000001 Z
b101111010000001 b
b11010100100100 &
b11010100100100 R
b11010100100100 B
b11010100100100 V
b11010100100100 _
1M
zi
0(
0L
zh
1I
ze
0)
0H
zd
b101111010000001 E
b101111010000001 Y
bz `
b1010000101111110 *
b1010000101111110 ?
b1010000101111110 C
b1010000101111110 W
bz ^
b11010100100100 O
b11010100100100 ]
bz k
b1100101011011011 '
b1100101011011011 A
b1100101011011011 N
b1100101011011011 \
bz j
1+
#55000
1i
1e
b101111010000001 `
b11010100100100 k
b11010100100100 O
b11010100100100 ]
b101111010000001 E
b101111010000001 Y
1I
1M
0(
0L
0h
0)
0H
0d
b1010000101111110 *
b1010000101111110 ?
b1010000101111110 C
b1010000101111110 W
b1010000101111110 ^
b1100101011011011 '
b1100101011011011 A
b1100101011011011 N
b1100101011011011 \
b1100101011011011 j
0Q
zm
1#
1P
zl
0K
zg
1$
1J
zf
b1010000101111110 G
b1010000101111110 [
bz c
b101111010000001 %
b101111010000001 T
b101111010000001 F
b101111010000001 Z
bz b
b1100101011011011 D
b1100101011011011 X
bz a
b11010100100100 &
b11010100100100 R
b11010100100100 B
b11010100100100 V
bz _
0+
#65000
1Q
b110011001110010 G
b110011001110010 [
b1000010011110010 D
b1000010011110010 X
0M
0i
1(
1L
1h
1I
1e
0)
0H
0d
b1001100110001101 E
b1001100110001101 Y
b1001100110001101 `
b110011001110010 *
b110011001110010 ?
b110011001110010 C
b110011001110010 W
b110011001110010 ^
b111101100001101 O
b111101100001101 ]
b111101100001101 k
b1000010011110010 '
b1000010011110010 A
b1000010011110010 N
b1000010011110010 \
b1000010011110010 j
0#
0P
b1001100110001101 %
b1001100110001101 T
b1001100110001101 F
b1001100110001101 Z
b111101100001101 &
b111101100001101 R
b111101100001101 B
b111101100001101 V
0/
b1001100110001101 -
b1001100110001101 @
b111101100001101 ,
b111101100001101 >
03
b1001100110001101 1
b111101100001101 0
b1 =
#85000
16
b110011001110010 4
b110011001110010 S
b1000010011110010 7
b1000010011110010 U
1:
b110011001110010 8
b1000010011110010 ;
#90000
1m
0g
b110011001110010 c
b1000010011110010 a
b1000010011110010 D
b1000010011110010 X
b110011001110010 G
b110011001110010 [
0K
1Q
0#
0P
0l
1$
1J
1f
b1001100110001101 %
b1001100110001101 T
b1001100110001101 F
b1001100110001101 Z
b1001100110001101 b
b111101100001101 &
b111101100001101 R
b111101100001101 B
b111101100001101 V
b111101100001101 _
0M
zi
1(
1L
zh
1I
ze
0)
0H
zd
b1001100110001101 E
b1001100110001101 Y
bz `
b110011001110010 *
b110011001110010 ?
b110011001110010 C
b110011001110010 W
bz ^
b111101100001101 O
b111101100001101 ]
bz k
b1000010011110010 '
b1000010011110010 A
b1000010011110010 N
b1000010011110010 \
bz j
1+
#110000
0i
1e
b1001100110001101 `
b111101100001101 k
b111101100001101 O
b111101100001101 ]
b1001100110001101 E
b1001100110001101 Y
1I
0M
1(
1L
1h
0)
0H
0d
b110011001110010 *
b110011001110010 ?
b110011001110010 C
b110011001110010 W
b110011001110010 ^
b1000010011110010 '
b1000010011110010 A
b1000010011110010 N
b1000010011110010 \
b1000010011110010 j
1Q
zm
0#
0P
zl
0K
zg
1$
1J
zf
b110011001110010 G
b110011001110010 [
bz c
b1001100110001101 %
b1001100110001101 T
b1001100110001101 F
b1001100110001101 Z
bz b
b1000010011110010 D
b1000010011110010 X
bz a
b111101100001101 &
b111101100001101 R
b111101100001101 B
b111101100001101 V
bz _
0+
#120000
0Q
1K
b11001011110010 G
b11001011110010 [
b1110011111110 D
b1110011111110 X
1M
1i
0(
0L
0h
0I
0e
1)
1H
1d
b1100110100001101 E
b1100110100001101 Y
b1100110100001101 `
b11001011110010 *
b11001011110010 ?
b11001011110010 C
b11001011110010 W
b11001011110010 ^
b1110001100000001 O
b1110001100000001 ]
b1110001100000001 k
b1110011111110 '
b1110011111110 A
b1110011111110 N
b1110011111110 \
b1110011111110 j
1#
1P
0$
0J
b1100110100001101 %
b1100110100001101 T
b1100110100001101 F
b1100110100001101 Z
b1110001100000001 &
b1110001100000001 R
b1110001100000001 B
b1110001100000001 V
1/
0.
b1100110100001101 -
b1100110100001101 @
b1110001100000001 ,
b1110001100000001 >
13
02
b1100110100001101 1
b1110001100000001 0
b10 =
#140000
06
15
b11001011110010 4
b11001011110010 S
b1110011111110 7
b1110011111110 U
0:
19
b11001011110010 8
b1110011111110 ;
#145000
0m
1g
b11001011110010 c
b1110011111110 a
b1110011111110 D
b1110011111110 X
b11001011110010 G
b11001011110010 [
1K
0Q
1#
1P
1l
0$
0J
0f
b1100110100001101 %
b1100110100001101 T
b1100110100001101 F
b1100110100001101 Z
b1100110100001101 b
b1110001100000001 &
b1110001100000001 R
b1110001100000001 B
b1110001100000001 V
b1110001100000001 _
1M
zi
0(
0L
zh
0I
ze
1)
1H
zd
b1100110100001101 E
b1100110100001101 Y
bz `
b11001011110010 *
b11001011110010 ?
b11001011110010 C
b11001011110010 W
bz ^
b1110001100000001 O
b1110001100000001 ]
bz k
b1110011111110 '
b1110011111110 A
b1110011111110 N
b1110011111110 \
bz j
1+
#165000
1i
0e
b1100110100001101 `
b1110001100000001 k
b1110001100000001 O
b1110001100000001 ]
b1100110100001101 E
b1100110100001101 Y
0I
1M
0(
0L
0h
1)
1H
1d
b11001011110010 *
b11001011110010 ?
b11001011110010 C
b11001011110010 W
b11001011110010 ^
b1110011111110 '
b1110011111110 A
b1110011111110 N
b1110011111110 \
b1110011111110 j
0Q
zm
1#
1P
zl
1K
zg
0$
0J
zf
b11001011110010 G
b11001011110010 [
bz c
b1100110100001101 %
b1100110100001101 T
b1100110100001101 F
b1100110100001101 Z
bz b
b1110011111110 D
b1110011111110 X
bz a
b1110001100000001 &
b1110001100000001 R
b1110001100000001 B
b1110001100000001 V
bz _
0+
#175000
1Q
0K
b100001110011 G
b100001110011 [
b1010100000010010 D
b1010100000010010 X
0M
0i
1(
1L
1h
1I
1e
0)
0H
0d
b1111011110001100 E
b1111011110001100 Y
b1111011110001100 `
b100001110011 *
b100001110011 ?
b100001110011 C
b100001110011 W
b100001110011 ^
b101011111101101 O
b101011111101101 ]
b101011111101101 k
b1010100000010010 '
b1010100000010010 A
b1010100000010010 N
b1010100000010010 \
b1010100000010010 j
0#
0P
1$
1J
b1111011110001100 %
b1111011110001100 T
b1111011110001100 F
b1111011110001100 Z
b101011111101101 &
b101011111101101 R
b101011111101101 B
b101011111101101 V
0/
1.
b1111011110001100 -
b1111011110001100 @
b101011111101101 ,
b101011111101101 >
03
12
b1111011110001100 1
b101011111101101 0
b11 =
#195000
16
05
b100001110011 4
b100001110011 S
b1010100000010010 7
b1010100000010010 U
1:
09
b100001110011 8
b1010100000010010 ;
#200000
1m
0g
b100001110011 c
b1010100000010010 a
b1010100000010010 D
b1010100000010010 X
b100001110011 G
b100001110011 [
0K
1Q
0#
0P
0l
1$
1J
1f
b1111011110001100 %
b1111011110001100 T
b1111011110001100 F
b1111011110001100 Z
b1111011110001100 b
b101011111101101 &
b101011111101101 R
b101011111101101 B
b101011111101101 V
b101011111101101 _
0M
zi
1(
1L
zh
1I
ze
0)
0H
zd
b1111011110001100 E
b1111011110001100 Y
bz `
b100001110011 *
b100001110011 ?
b100001110011 C
b100001110011 W
bz ^
b101011111101101 O
b101011111101101 ]
bz k
b1010100000010010 '
b1010100000010010 A
b1010100000010010 N
b1010100000010010 \
bz j
1+
#220000
0i
1e
b1111011110001100 `
b101011111101101 k
b101011111101101 O
b101011111101101 ]
b1111011110001100 E
b1111011110001100 Y
1I
0M
1(
1L
1h
0)
0H
0d
b100001110011 *
b100001110011 ?
b100001110011 C
b100001110011 W
b100001110011 ^
b1010100000010010 '
b1010100000010010 A
b1010100000010010 N
b1010100000010010 \
b1010100000010010 j
1Q
zm
0#
0P
zl
0K
zg
1$
1J
zf
b100001110011 G
b100001110011 [
bz c
b1111011110001100 %
b1111011110001100 T
b1111011110001100 F
b1111011110001100 Z
bz b
b1010100000010010 D
b1010100000010010 X
bz a
b101011111101101 &
b101011111101101 R
b101011111101101 B
b101011111101101 V
bz _
0+
#230000
0Q
b10110101010101 G
b10110101010101 [
b111101100111010 D
b111101100111010 X
1M
1i
0(
0L
0h
1I
1e
0)
0H
0d
b1101001010101010 E
b1101001010101010 Y
b1101001010101010 `
b10110101010101 *
b10110101010101 ?
b10110101010101 C
b10110101010101 W
b10110101010101 ^
b1000010011000101 O
b1000010011000101 ]
b1000010011000101 k
b111101100111010 '
b111101100111010 A
b111101100111010 N
b111101100111010 \
b111101100111010 j
1#
1P
b1101001010101010 %
b1101001010101010 T
b1101001010101010 F
b1101001010101010 Z
b1000010011000101 &
b1000010011000101 R
b1000010011000101 B
b1000010011000101 V
1/
b1101001010101010 -
b1101001010101010 @
b1000010011000101 ,
b1000010011000101 >
13
b1101001010101010 1
b1000010011000101 0
b100 =
#250000
06
b10110101010101 4
b10110101010101 S
b111101100111010 7
b111101100111010 U
0:
b10110101010101 8
b111101100111010 ;
